gato/.DS_Store
gato/__init__.py
gato/model.py
gato_torch-0.0.2.dist-info/LICENSE
gato_torch-0.0.2.dist-info/WHEEL
gato_torch-0.0.2.dist-info/METADATA
gato_torch-0.0.2.dist-info/RECORD
