Metadata-Version: 2.1
Name: gato-torch
Version: 0.0.2
Summary: Gato: A Generalist Agent
Home-page: https://github.com/kyegomez/GATO
License: MIT
Keywords: deep learning,gato,tensorflow
Author: Kye Gomez
Author-email: kye@apac.ai
Requires-Python: >=3.10,<4.0
Classifier: Development Status :: 4 - Beta
Classifier: Intended Audience :: Developers
Classifier: License :: OSI Approved :: MIT License
Classifier: Programming Language :: Python :: 3
Classifier: Programming Language :: Python :: 3.10
Classifier: Programming Language :: Python :: 3.11
Classifier: Programming Language :: Python :: 3.10
Classifier: Topic :: Scientific/Engineering :: Artificial Intelligence
Requires-Dist: einops
Requires-Dist: torch
Requires-Dist: zetascale
